farmi/__init__.py
farmi/directory_service.py
farmi/farmi.py
farmi/farmi_file.py
farmi/publisher.py
farmi/serialization.py
farmi/subscriber.py
farmi/utils.py
farmi-3.1.4.data/scripts/farmi-server
test/__init__.py
test/test_directory_service.py
test/test_farmi.py
test/test_publisher.py
test/test_serializer.py
test/test_subscriber.py
test/test_utils.py
farmi-3.1.4.dist-info/METADATA
farmi-3.1.4.dist-info/WHEEL
farmi-3.1.4.dist-info/top_level.txt
farmi-3.1.4.dist-info/RECORD
