Metadata-Version: 2.1
Name: farmi
Version: 3.1.4
Summary: Multisensory processing framework 
Home-page: UNKNOWN
Author: Patrik Jonell
Author-email: pjjonell@kth.se
License: UNKNOWN
Platform: UNKNOWN
Requires-Python: >=3
Requires-Dist: pyzmq
Requires-Dist: msgpack
Requires-Dist: msgpack-numpy
Requires-Dist: lz4
